ethical_engine/__init__.py
ethical_engine/constraint.py
ethical_engine/detectors/__init__.py
ethical_engine/detectors/autonomy_violation.py
ethical_engine/detectors/defense_detection.py
ethical_engine/detectors/harm_detection.py
ethical_engine/detectors/military_detection.py
ethical_engine/ledger/__init__.py
ethical_engine/ledger/logger.py
ethical_ai_framework-1.0.8.dist-info/METADATA
ethical_ai_framework-1.0.8.dist-info/WHEEL
ethical_ai_framework-1.0.8.dist-info/top_level.txt
ethical_ai_framework-1.0.8.dist-info/RECORD
