Metadata-Version: 2.4
Name: ethical-ai-framework
Version: 1.0.8
Summary: A transparent, consent-based, non-weaponizable ethical AI framework
Author: Cherokee
License: MIT
Classifier: Programming Language :: Python :: 3
Classifier: License :: OSI Approved :: MIT License
Classifier: Intended Audience :: Developers
Classifier: Operating System :: OS Independent
Requires-Python: >=3.7
Dynamic: author
Dynamic: classifier
Dynamic: description
Dynamic: description-content-type
Dynamic: license
Dynamic: requires-python
Dynamic: summary
